pymicro/__init__.py
pymicro/apps/ImageViewer.py
pymicro/apps/View.py
pymicro/apps/__init__.py
pymicro/core/__init__.py
pymicro/core/features.py
pymicro/core/global_variables.py
pymicro/core/samples.py
pymicro/core/utils/SDAmitexUtils.py
pymicro/core/utils/SDGridUtils.py
pymicro/core/utils/SDUtilsGlobals.py
pymicro/core/utils/__init__.py
pymicro/core/utils/templateUtils.py
pymicro/core/utils/SDZsetUtils/SDZset.py
pymicro/core/utils/SDZsetUtils/SDZsetFEA.py
pymicro/core/utils/SDZsetUtils/SDmeshers.py
pymicro/core/utils/SDZsetUtils/__init__.py
pymicro/crystal/__init__.py
pymicro/crystal/ebsd.py
pymicro/crystal/lattice.py
pymicro/crystal/microstructure.py
pymicro/crystal/quaternion.py
pymicro/crystal/rotation.py
pymicro/crystal/texture.py
pymicro/crystal/view.py
pymicro/examples/__init__.py
pymicro/examples/3d_visualisation/2-6-2_30k00_c1_3d.png
pymicro/examples/3d_visualisation/2-6-2_30k00_c1_3d.py
pymicro/examples/3d_visualisation/AuCu_crystal.png
pymicro/examples/3d_visualisation/AuCu_crystal.py
pymicro/examples/3d_visualisation/__init__.py
pymicro/examples/3d_visualisation/cracked_single_crystal_with_slip_systems.png
pymicro/examples/3d_visualisation/cracked_single_crystal_with_slip_systems.py
pymicro/examples/3d_visualisation/crystal_lattice_3d.png
pymicro/examples/3d_visualisation/crystal_lattice_3d.py
pymicro/examples/3d_visualisation/cubic_crystal_3d.png
pymicro/examples/3d_visualisation/cubic_crystal_3d.py
pymicro/examples/3d_visualisation/grain_3d_planes.png
pymicro/examples/3d_visualisation/grain_3d_planes.py
pymicro/examples/3d_visualisation/grain_hkl_3d.png
pymicro/examples/3d_visualisation/grain_hkl_3d.py
pymicro/examples/3d_visualisation/hcp_crystal_3d.png
pymicro/examples/3d_visualisation/hcp_crystal_3d.py
pymicro/examples/3d_visualisation/hexagonal_crystal_3d.png
pymicro/examples/3d_visualisation/hexagonal_crystal_3d.py
pymicro/examples/3d_visualisation/mousse_3d.png
pymicro/examples/3d_visualisation/mousse_3d.py
pymicro-0.6.1.dist-info/LICENSE.md
pymicro-0.6.1.dist-info/METADATA
pymicro-0.6.1.dist-info/WHEEL
pymicro-0.6.1.dist-info/top_level.txt
pymicro-0.6.1.dist-info/RECORD
