Metadata-Version: 2.1
Name: pymicro
Version: 0.6.1
Summary: An open-source Python package to work with material microstructures and 3d data sets
Home-page: https://github.com/heprom/pymicro
Author: Henry Proudhon
Author-email: henry.proudhon@mines-paristech.fr
License: MIT license
Classifier: Programming Language :: Python :: 3
Classifier: License :: OSI Approved :: MIT License
Classifier: Operating System :: OS Independent
Classifier: Development Status :: 4 - Beta
Requires-Python: >=3.6
License-File: LICENSE.md
Requires-Dist: numpy <2.0.0
Requires-Dist: scipy
Requires-Dist: scikit-image
Requires-Dist: scikit-learn
Requires-Dist: matplotlib
Requires-Dist: vtk
Requires-Dist: h5py
Requires-Dist: lxml
Requires-Dist: tables
Requires-Dist: networkx
Requires-Dist: tqdm
Requires-Dist: requests
Requires-Dist: pytest
Requires-Dist: BasicToolsFrozen
Requires-Dist: PyQt5
